odoo/addons/ssi_operating_unit_mixin/README.rst
odoo/addons/ssi_operating_unit_mixin/__init__.py
odoo/addons/ssi_operating_unit_mixin/__manifest__.py
odoo/addons/ssi_operating_unit_mixin/models/__init__.py
odoo/addons/ssi_operating_unit_mixin/models/ir_sequence.py
odoo/addons/ssi_operating_unit_mixin/models/mixin_multiple_operating_unit.py
odoo/addons/ssi_operating_unit_mixin/models/mixin_single_operating_unit.py
odoo/addons/ssi_operating_unit_mixin/security/ir_rule_data.xml
odoo/addons/ssi_operating_unit_mixin/static/description/icon.png
odoo/addons/ssi_operating_unit_mixin/views/ir_sequence_views.xml
odoo14_addon_ssi_operating_unit_mixin-14.0.1.2.0.dist-info/METADATA
odoo14_addon_ssi_operating_unit_mixin-14.0.1.2.0.dist-info/WHEEL
odoo14_addon_ssi_operating_unit_mixin-14.0.1.2.0.dist-info/top_level.txt
odoo14_addon_ssi_operating_unit_mixin-14.0.1.2.0.dist-info/RECORD
